Aries/storage/__init__.py
Aries/storage/base.py
Aries/storage/cloud.py
Aries/storage/file.py
Aries/storage/gs.py
Aries/storage/io.py
Aries/storage/s3.py
Aries/storage/web.py
Aries_storage-0.1.330.dist-info/METADATA
Aries_storage-0.1.330.dist-info/WHEEL
Aries_storage-0.1.330.dist-info/top_level.txt
Aries_storage-0.1.330.dist-info/RECORD
