Metadata-Version: 2.1
Name: Aries-storage
Version: 0.1.330
Summary: Read and write files on Google Cloud Storage and Amazon S3 as if they are on local computer.
Home-page: https://github.com/qiuosier/Aries
Author: Qiu Qin
Author-email: qiuosier@gmail.com
License: UNKNOWN
Platform: UNKNOWN
Classifier: Programming Language :: Python :: 3
Classifier: License :: OSI Approved :: MIT License
Classifier: Operating System :: OS Independent
Requires-Python: >=3.6
Requires-Dist: Aries-core (==0.1.330)
Requires-Dist: google-cloud-core (>=1.3.0)
Requires-Dist: google-cloud-storage (>=1.26.0)
Requires-Dist: boto3 (>=1.14.9)
